[
  {
    "grammar": "～たばかり",
    "formation": null,
    "examples": []
  },
  {
    "grammar": "～ようになる",
    "formation": null,
    "examples": []
  },
  {
    "grammar": "～ことになる",
    "formation": null,
    "examples": []
  },
  {
    "grammar": "～とても～ない",
    "formation": null,
    "examples": []
  },
  {
    "grammar": "～らしい",
    "formation": null,
    "examples": []
  },
  {
    "grammar": "～て初めて",
    "formation": null,
    "examples": []
  },
  {
    "grammar": "～ないで",
    "formation": null,
    "examples": []
  },
  {
    "grammar": "～によって",
    "formation": null,
    "examples": []
  },
  {
    "grammar": "～のような",
    "formation": null,
    "examples": []
  },
  {
    "grammar": "～ば～ほど",
    "formation": null,
    "examples": []
  },
  {
    "grammar": "N+ばかり",
    "formation": null,
    "examples": []
  },
  {
    "grammar": "～は～で有名",
    "formation": null,
    "examples": []
  },
  {
    "grammar": "N+を始め",
    "formation": null,
    "examples": []
  },
  {
    "grammar": "的",
    "formation": null,
    "examples": []
  },
  {
    "grammar": "～は～くらいです",
    "formation": null,
    "examples": []
  },
  {
    "grammar": "～さえ～ば",
    "formation": null,
    "examples": []
  },
  {
    "grammar": "ほど",
    "formation": null,
    "examples": []
  },
  {
    "grammar": "まま",
    "formation": null,
    "examples": []
  },
  {
    "grammar": "わざわざ",
    "formation": null,
    "examples": []
  },
  {
    "grammar": "～としたら",
    "formation": null,
    "examples": []
  },
  {
    "grammar": "～たものだ",
    "formation": null,
    "examples": []
  },
  {
    "grammar": "～たて",
    "formation": null,
    "examples": []
  },
  {
    "grammar": "～ぐらい",
    "formation": null,
    "examples": []
  },
  {
    "grammar": "～かえって",
    "formation": null,
    "examples": []
  },
  {
    "grammar": "～には～の～がある",
    "formation": null,
    "examples": []
  },
  {
    "grammar": "～っぽい",
    "formation": null,
    "examples": []
  },
  {
    "grammar": "～に関する",
    "formation": null,
    "examples": []
  },
  {
    "grammar": "まさか",
    "formation": null,
    "examples": []
  },
  {
    "grammar": "まい",
    "formation": null,
    "examples": []
  },
  {
    "grammar": "きり",
    "formation": null,
    "examples": []
  },
  {
    "grammar": "いったい（一体）",
    "formation": null,
    "examples": []
  },
  {
    "grammar": "ふり",
    "formation": null,
    "examples": []
  },
  {
    "grammar": "どうやら",
    "formation": null,
    "examples": []
  },
  {
    "grammar": "おかげで",
    "formation": null,
    "examples": []
  },
  {
    "grammar": "さらに（更に）",
    "formation": null,
    "examples": []
  },
  {
    "grammar": "すでに（既に）",
    "formation": null,
    "examples": []
  },
  {
    "grammar": "つい",
    "formation": null,
    "examples": []
  },
  {
    "grammar": "むしろ",
    "formation": null,
    "examples": []
  },
  {
    "grammar": "さえ",
    "formation": null,
    "examples": []
  },
  {
    "grammar": "～になれる",
    "formation": null,
    "examples": []
  },
  {
    "grammar": "～に違いない",
    "formation": null,
    "examples": []
  },
  {
    "grammar": "なかなか",
    "formation": null,
    "examples": []
  },
  {
    "grammar": "～ために",
    "formation": null,
    "examples": []
  },
  {
    "grammar": "～ず",
    "formation": null,
    "examples": []
  },
  {
    "grammar": "～によると",
    "formation": null,
    "examples": []
  },
  {
    "grammar": "～代わり",
    "formation": null,
    "examples": []
  },
  {
    "grammar": "ようにする",
    "formation": null,
    "examples": []
  },
  {
    "grammar": "～始める",
    "formation": null,
    "examples": []
  },
  {
    "grammar": "～ても",
    "formation": null,
    "examples": []
  },
  {
    "grammar": "～として",
    "formation": null,
    "examples": []
  },
  {
    "grammar": "ように",
    "formation": null,
    "examples": []
  },
  {
    "grammar": "こそ",
    "formation": null,
    "examples": []
  },
  {
    "grammar": "～ないうちに",
    "formation": null,
    "examples": []
  },
  {
    "grammar": "どうしても",
    "formation": null,
    "examples": []
  },
  {
    "grammar": "～がち",
    "formation": null,
    "examples": []
  },
  {
    "grammar": "せいぜい",
    "formation": null,
    "examples": []
  },
  {
    "grammar": "限る",
    "formation": null,
    "examples": []
  },
  {
    "grammar": "～とともに～",
    "formation": null,
    "examples": []
  },
  {
    "grammar": "～たび～",
    "formation": null,
    "examples": []
  },
  {
    "grammar": "すぎない（過ぎない）",
    "formation": null,
    "examples": []
  },
  {
    "grammar": "おいて（於いて）",
    "formation": null,
    "examples": []
  },
  {
    "grammar": "～げ",
    "formation": null,
    "examples": []
  },
  {
    "grammar": "つもりで",
    "formation": null,
    "examples": []
  }
]
